{
	"info": {
		"_postman_id": "f9d1db1f-9140-4208-b993-651f2a174dd8",
		"name": "Rust VPN",
		"schema": "https://schema.getpostman.com/json/collection/v2.1.0/collection.json",
		"_exporter_id": "25521999"
	},
	"item": [
		{
			"name": "client",
			"item": [
				{
					"name": "signup",
					"request": {
						"method": "POST",
						"header": [],
						"body": {
							"mode": "raw",
							"raw": "{\r\n    \"email\": \"johnDoe@gmail.com\",\r\n    \"username\": \"JohnDoe\",\r\n    \"password\": \"bestpassword\",\r\n    \"ip\": \"255.255.255.255\"\r\n}",
							"options": {
								"raw": {
									"language": "json"
								}
							}
						},
						"url": {
							"raw": "localhost:8080/signup",
							"host": [
								"localhost"
							],
							"port": "8080",
							"path": [
								"signup"
							]
						}
					},
					"response": []
				},
				{
					"name": "login with client",
					"protocolProfileBehavior": {
						"disableBodyPruning": true
					},
					"request": {
						"method": "GET",
						"header": [],
						"body": {
							"mode": "raw",
							"raw": "{\n    \"email\": \"johnDoe@gmail.com\",\n    \"password\": \"bestpassword\"\n}",
							"options": {
								"raw": {
									"language": "json"
								}
							}
						},
						"url": {
							"raw": "localhost:8080/user/users",
							"host": [
								"localhost"
							],
							"port": "8080",
							"path": [
								"user",
								"users"
							]
						}
					},
					"response": []
				},
				{
					"name": "allowedIpForClient",
					"request": {
						"method": "POST",
						"header": [],
						"body": {
							"mode": "raw",
							"raw": "{\n    \"ip\": \"192.168.1.1\",\n    \"email\": \"johnDoe@gmail.com\"\n}",
							"options": {
								"raw": {
									"language": "json"
								}
							}
						},
						"url": {
							"raw": "localhost:8080/user/addIpToPeer",
							"host": [
								"localhost"
							],
							"port": "8080",
							"path": [
								"user",
								"addIpToPeer"
							]
						}
					},
					"response": []
				}
			]
		},
		{
			"name": "admin",
			"item": [
				{
					"name": "login with admin",
					"request": {
						"method": "POST",
						"header": [],
						"body": {
							"mode": "raw",
							"raw": "{\n    \"email\": \"alan2@gmail.com\",\n    \"password\": \"supersecretpassword\"\n}",
							"options": {
								"raw": {
									"language": "json"
								}
							}
						},
						"url": {
							"raw": "localhost:8080/login",
							"host": [
								"localhost"
							],
							"port": "8080",
							"path": [
								"login"
							]
						}
					},
					"response": []
				},
				{
					"name": "createPeer",
					"request": {
						"method": "POST",
						"header": [],
						"body": {
							"mode": "raw",
							"raw": "{\n    \"email\": \"johnDoe@gmail.com\"\n}",
							"options": {
								"raw": {
									"language": "json"
								}
							}
						},
						"url": {
							"raw": "localhost:8080/admin/createPeer",
							"host": [
								"localhost"
							],
							"port": "8080",
							"path": [
								"admin",
								"createPeer"
							]
						}
					},
					"response": []
				},
				{
					"name": "getAllPeers",
					"request": {
						"method": "GET",
						"header": [],
						"url": {
							"raw": "localhost:8080/admin/peers",
							"host": [
								"localhost"
							],
							"port": "8080",
							"path": [
								"admin",
								"peers"
							]
						}
					},
					"response": []
				},
				{
					"name": "getAllUsers",
					"request": {
						"method": "GET",
						"header": [],
						"url": {
							"raw": "localhost:8080/admin/users",
							"host": [
								"localhost"
							],
							"port": "8080",
							"path": [
								"admin",
								"users"
							]
						}
					},
					"response": []
				}
			]
		}
	]
}